{"archery_kid": 0, "bouncing on trampoline_kid": 1, "bowling_kid": 2, "cartwheeling_kid": 3, "catching or throwing baseball_kid": 4, "catching or throwing frisbee_kid": 5, "catching or throwing softball_kid": 6, "dribbling basketball_kid": 7, "dunking basketball_kid": 8, "hitting baseball_kid": 9, "juggling soccer ball_kid": 10, "kicking soccer ball_kid": 11, "parkour_kid": 12, "playing badminton_kid": 13, "playing basketball_kid": 14, "playing cricket_kid": 15, "playing tennis_kid": 16, "playing volleyball_kid": 17, "shooting basketball_kid": 18, "somersaulting_kid": 19, "water skiing_kid": 20}